django_lookup_tables-0.15.3.dist-info/METADATA
django_lookup_tables-0.15.3.dist-info/RECORD
django_lookup_tables-0.15.3.dist-info/WHEEL
django_lookup_tables-0.15.3.dist-info/top_level.txt
lookup_tables/__init__.py
lookup_tables/admin.py
lookup_tables/apps.py
lookup_tables/conf.py
lookup_tables/drf_fields.py
lookup_tables/fields.py
lookup_tables/models.py
lookup_tables/migrations/0001_initial.py
lookup_tables/migrations/0001_initial_squashed_0005_auto_20180927_2134.py
lookup_tables/migrations/0002_table_ref_field.py
lookup_tables/migrations/0003_auto_20180614_2034.py
lookup_tables/migrations/0004_auto_20180926_1753.py
lookup_tables/migrations/0005_auto_20180927_2134.py
lookup_tables/migrations/__init__.py
sample_app/__init__.py
sample_app/admin.py
sample_app/models.py
sample_app/serializers.py
sample_app/views.py
sample_app/migrations/0001_initial.py
sample_app/migrations/__init__.py
tests/__init__.py
tests/mixins.py
tests/settings.py
tests/test_drf_fields.py
tests/test_fields.py
tests/test_models.py
tests/urls.py
tests/utils.py
